j2cli/cli.py
j2cli/filters.py
j2cli/util.py
j2y-0.3.0.dist-info/LICENSE
j2y-0.3.0.dist-info/METADATA
j2y-0.3.0.dist-info/WHEEL
j2y-0.3.0.dist-info/entry_points.txt
j2y-0.3.0.dist-info/top_level.txt
j2y-0.3.0.dist-info/RECORD
