Metadata-Version: 2.1
Name: j2y
Version: 0.3.0
Summary: A command line interface for rendering Jinja2 templates.
Home-page: https://github.com/chaudum/j2y
Author: Christian Haudum
Author-email: christian@christianhaudum.at
License: Apache License 2.0
Platform: any
Classifier: Development Status :: 4 - Beta
Classifier: Intended Audience :: Developers
Classifier: License :: OSI Approved :: Apache Software License
Classifier: Operating System :: OS Independent
Classifier: Programming Language :: Python
Classifier: Programming Language :: Python :: 3
Classifier: Programming Language :: Python :: 3.6
Classifier: Programming Language :: Python :: 3.7
Classifier: Programming Language :: Python :: 3.8
Requires-Python: >=3.6
Requires-Dist: Jinja2 (<2.12,>=2.11)
Requires-Dist: PyYAML (==5.3)
Requires-Dist: pyhcl (==0.4.0)
Provides-Extra: docs
Requires-Dist: Sphinx (<1.9,>=1.8) ; extra == 'docs'
Provides-Extra: test
Requires-Dist: pytest (>=5.4) ; extra == 'test'
Requires-Dist: pytest-flake8 ; extra == 'test'
Requires-Dist: pytest-black ; extra == 'test'
Requires-Dist: pytest-mypy ; extra == 'test'
